MANIFEST.in
README.rst
setup.py
ohmu/__init__.py
ohmu/fs.py
ohmu/test_fs.py
ohmu/test_init.py
ohmu/test_utils.py
ohmu/test_views.py
ohmu/utils.py
ohmu/views.py
ohmu.egg-info/PKG-INFO
ohmu.egg-info/SOURCES.txt
ohmu.egg-info/dependency_links.txt
ohmu.egg-info/entry_points.txt
ohmu.egg-info/requires.txt
ohmu.egg-info/top_level.txt