Metadata-Version: 1.0
Name: ohmu
Version: 1.1.0
Summary: View space usage in your terminal.
Home-page: http://github.com/paul-nechifor/ohmu
Author: Paul Nechifor
Author-email: paul@nechifor.net
License: MIT
Keywords: space usage
Platform: UNKNOWN
